tianxiu2b2t/collections.py
tianxiu2b2t/env.py
tianxiu2b2t/logging.py
tianxiu2b2t/objectid.py
tianxiu2b2t/parser.py
tianxiu2b2t/units.py
tianxiu2b2t/utils.py
tianxiu2b2t/anyio/__init__.py
tianxiu2b2t/anyio/concurrency.py
tianxiu2b2t/anyio/exceptions.py
tianxiu2b2t/anyio/future.py
tianxiu2b2t/anyio/lock.py
tianxiu2b2t/anyio/queues.py
tianxiu2b2t/anyio/streams/__init__.py
tianxiu2b2t/anyio/streams/abc.py
tianxiu2b2t/anyio/streams/listener.py
tianxiu2b2t/anyio/streams/proxy.py
tianxiu2b2t/anyio/streams/tls.py
tianxiu2b2t/http/asgi.py
tianxiu2b2t/http/protocol/auto.py
tianxiu2b2t/http/protocol/exceptions.py
tianxiu2b2t/http/protocol/h1.py
tianxiu2b2t/http/protocol/h2.py
tianxiu2b2t/http/protocol/streams.py
tianxiu2b2t/http/protocol/types.py
tianxiu2b2t/http/protocol/websockets.py
tianxiu2b2t_utils-0.1.37.dist-info/licenses/LICENSE
tianxiu2b2t_utils-0.1.37.dist-info/METADATA
tianxiu2b2t_utils-0.1.37.dist-info/WHEEL
tianxiu2b2t_utils-0.1.37.dist-info/top_level.txt
tianxiu2b2t_utils-0.1.37.dist-info/RECORD
