Metadata-Version: 2.4
Name: tianxiu2b2t-utils
Version: 0.1.37
Summary: A collection of utilities for the tianxiu2b2t packages.
Author-email: tianxiu2b2t <atianxiua@163.com>
License: MIT
Requires-Python: >=3.10
License-File: LICENSE
Requires-Dist: anyio>=4.9.0
Requires-Dist: dotenv>=0.9.9
Requires-Dist: h11>=0.16.0
Requires-Dist: h2>=4.2.0
Requires-Dist: wsproto>=1.2.0
Dynamic: license-file
